snowflake/operators/__init__.py
snowflake/operators/snowpark_submit/__init__.py
snowflake/operators/snowpark_submit/connection_utils.py
snowflake/operators/snowpark_submit/snowpark_submit_operator.py
snowflake/operators/snowpark_submit/snowpark_submit_status_operator.py
snowflake/snowpark_submit/__init__.py
snowflake/snowpark_submit/api.py
snowflake/snowpark_submit/config.py
snowflake/snowpark_submit/constants.py
snowflake/snowpark_submit/file_path.py
snowflake/snowpark_submit/snowpark_submit.py
snowflake/snowpark_submit/cluster_mode/__init__.py
snowflake/snowpark_submit/cluster_mode/job_runner.py
snowflake/snowpark_submit/cluster_mode/spark_connect/spark_connect_job_runner.py
snowflake/snowpark_submit/cluster_mode/spark_connect/resources/spcs_spec.template.yaml
snowpark_submit-1.9.0.dist-info/licenses/LICENSE.txt
snowpark_submit-1.9.0.dist-info/METADATA
snowpark_submit-1.9.0.dist-info/WHEEL
snowpark_submit-1.9.0.dist-info/entry_points.txt
snowpark_submit-1.9.0.dist-info/top_level.txt
snowpark_submit-1.9.0.dist-info/RECORD
