Metadata-Version: 2.4
Name: snowpark-submit
Version: 1.9.0
Summary: Snowpark Submit
Author: Snowflake, Inc
License: Apache License, Version 2.0
Requires-Python: >=3.10,<3.13
License-File: LICENSE.txt
Requires-Dist: snowflake-snowpark-python>=1.32.0
Requires-Dist: pyyaml<7.0.0,>=6.0.2
Dynamic: author
Dynamic: description
Dynamic: description-content-type
Dynamic: license
Dynamic: license-file
Dynamic: requires-dist
Dynamic: requires-python
Dynamic: summary
